{
	"type": "minecraft:block",
	"pools": [
		{
			"rolls": 1,
			"entries": [
				{
					"type": "minecraft:item",
					"name": "fossils:junk_fossil",
					"weight": 299,
					"quality": -5
				},
				{
					"type": "minecraft:tag",
					"name": "fossils:quaternary_fossils",
					"weight": 200,
					"expand": true,
					"quality": 5
				},
				{
					"type": "minecraft:tag",
					"name": "fossils:fossils_music_discs",
					"expand": true
				}
			]
		}
	],
	"random_sequence": "fossils:block/quaternary_fossil_ore"
}