{
  "parent": "fossils:fossils/general/plesiosauroidea",
  "criteria": {
    "finish_plesiosaurus": {
      "conditions": {
        "location": [
          {
            "condition": "minecraft:location_check",
            "predicate": {
              "block": {
                "blocks": [
                  "fossils:plesiosaurus_fossil"
                ],
                "state": {
                  "fossil_level": "9"
                }
              }
            }
          },
          {
            "condition": "minecraft:match_tool",
            "predicate": {
              "items": [
                "fossils:plesiosaurus_fossil"
              ]
            }
          }
        ]
      },
      "trigger": "minecraft:item_used_on_block"
    }
  },
  "display": {
    "announce_to_chat": true,
    "description": {
      "translate": "advancements.fossils.plesiosaurus.description"
    },
    "frame": "goal",
    "hidden": false,
    "icon": {
      "item": "fossils:plesiosaurus_fossil"
    },
    "show_toast": true,
    "title": {
      "translate": "advancements.fossils.plesiosaurus.title"
    }
  },
  "requirements": [
    [
      "finish_plesiosaurus"
    ]
  ],
  "rewards": {
    "experience": 100
  },
  "sends_telemetry_event": true
}